edx_zoom/__init__.py
edx_zoom/admin.py
edx_zoom/apps.py
edx_zoom/models.py
edx_zoom/tabs.py
edx_zoom/utils.py
edx_zoom/zoom_consumer.py
edx_zoom/static/css/student.css
edx_zoom/templates/author.html
edx_zoom/templates/lti_iframe.html
edx_zoom/templates/student.html
edx_zoom-2.1.0.dist-info/LICENSE
edx_zoom-2.1.0.dist-info/METADATA
edx_zoom-2.1.0.dist-info/NOTICE
edx_zoom-2.1.0.dist-info/WHEEL
edx_zoom-2.1.0.dist-info/entry_points.txt
edx_zoom-2.1.0.dist-info/top_level.txt
edx_zoom-2.1.0.dist-info/RECORD
